{
    "contributors": null, 
    "coordinates": null, 
    "created_at": "Tue Apr 28 16:23:22 +0000 2015", 
    "entities": {
        "hashtags": [], 
        "symbols": [], 
        "urls": [], 
        "user_mentions": [
            {
                "id": 1339835893, 
                "id_str": "1339835893", 
                "indices": [
                    3, 
                    18
                ], 
                "name": "Hillary Clinton", 
                "screen_name": "HillaryClinton"
            }
        ]
    }, 
    "favorite_count": 0, 
    "favorited": false, 
    "geo": null, 
    "id": 593088124005265408, 
    "id_str": "593088124005265408", 
    "in_reply_to_screen_name": null, 
    "in_reply_to_status_id": null, 
    "in_reply_to_status_id_str": null, 
    "in_reply_to_user_id": null, 
    "in_reply_to_user_id_str": null, 
    "lang": "en", 
    "place": null, 
    "retweet_count": 1349, 
    "retweeted": false, 
    "retweeted_status": {
        "contributors": null, 
        "coordinates": null, 
        "created_at": "Sat Apr 25 15:44:35 +0000 2015", 
        "entities": {
            "hashtags": [], 
            "symbols": [], 
            "urls": [], 
            "user_mentions": []
        }, 
        "favorite_count": 2932, 
        "favorited": false, 
        "geo": null, 
        "id": 591991199424208896, 
        "id_str": "591991199424208896", 
        "in_reply_to_screen_name": null, 
        "in_reply_to_status_id": null, 
        "in_reply_to_status_id_str": null, 
        "in_reply_to_user_id": null, 
        "in_reply_to_user_id_str": null, 
        "lang": "en", 
        "place": null, 
        "retweet_count": 1349, 
        "retweeted": false, 
        "source": "<a href=\"http://twitter.com/download/iphone\" rel=\"nofollow\">Twitter for iPhone</a>", 
        "text": "My thoughts and prayers are with the people of Nepal. \u2013H", 
        "truncated": false, 
        "user": {
            "contributors_enabled": false, 
            "created_at": "Tue Apr 09 18:04:35 +0000 2013", 
            "default_profile": false, 
            "default_profile_image": false, 
            "description": "Wife, mom, grandma, women+kids advocate, FLOTUS, Senator, SecState, hair icon, pantsuit aficionado, 2016 presidential candidate. Tweets from Hillary signed \u2013H", 
            "entities": {
                "description": {
                    "urls": []
                }, 
                "url": {
                    "urls": [
                        {
                            "display_url": "hillaryclinton.com", 
                            "expanded_url": "http://www.hillaryclinton.com", 
                            "indices": [
                                0, 
                                22
                            ], 
                            "url": "http://t.co/ESBw0Arq44"
                        }
                    ]
                }
            }, 
            "favourites_count": 2, 
            "follow_request_sent": false, 
            "followers_count": 3442309, 
            "following": false, 
            "friends_count": 14, 
            "geo_enabled": false, 
            "id": 1339835893, 
            "id_str": "1339835893", 
            "is_translation_enabled": false, 
            "is_translator": false, 
            "lang": "en", 
            "listed_count": 15809, 
            "location": "New York", 
            "name": "Hillary Clinton", 
            "notifications": false, 
            "profile_background_color": "0057B8", 
            "profile_background_image_url": "http://abs.twimg.com/images/themes/theme1/bg.png", 
            "profile_background_image_url_https": "https://abs.twimg.com/images/themes/theme1/bg.png", 
            "profile_background_tile": false, 
            "profile_banner_url": "https://pbs.twimg.com/profile_banners/1339835893/1428866827", 
            "profile_image_url": "http://pbs.twimg.com/profile_images/593032903107485696/u7GWaekZ_normal.png", 
            "profile_image_url_https": "https://pbs.twimg.com/profile_images/593032903107485696/u7GWaekZ_normal.png", 
            "profile_link_color": "0057B8", 
            "profile_sidebar_border_color": "000000", 
            "profile_sidebar_fill_color": "000000", 
            "profile_text_color": "000000", 
            "profile_use_background_image": false, 
            "protected": false, 
            "screen_name": "HillaryClinton", 
            "statuses_count": 244, 
            "time_zone": "Eastern Time (US & Canada)", 
            "url": "http://t.co/ESBw0Arq44", 
            "utc_offset": -14400, 
            "verified": true
        }
    }, 
    "source": "<a href=\"http://twitter.com\" rel=\"nofollow\">Twitter Web Client</a>", 
    "text": "RT @HillaryClinton: My thoughts and prayers are with the people of Nepal. \u2013H", 
    "truncated": false, 
    "user": {
        "contributors_enabled": false, 
        "created_at": "Fri Jun 19 03:45:41 +0000 2009", 
        "default_profile": false, 
        "default_profile_image": false, 
        "description": "I Think, I Feel, I Am!. Adam Lambert is My Music Passion & Human Rights For All Is What I Stand For! I am Not Afraid To Have An Opinion and To Express it!", 
        "entities": {
            "description": {
                "urls": []
            }, 
            "url": {
                "urls": [
                    {
                        "display_url": "adamlambertStorm.com", 
                        "expanded_url": "http://adamlambertStorm.com", 
                        "indices": [
                            0, 
                            22
                        ], 
                        "url": "http://t.co/eSqsUGB9Up"
                    }
                ]
            }
        }, 
        "favourites_count": 8960, 
        "follow_request_sent": false, 
        "followers_count": 3111, 
        "following": false, 
        "friends_count": 2669, 
        "geo_enabled": true, 
        "id": 48599448, 
        "id_str": "48599448", 
        "is_translation_enabled": false, 
        "is_translator": false, 
        "lang": "en", 
        "listed_count": 85, 
        "location": "New York City", 
        "name": "Barbara", 
        "notifications": false, 
        "profile_background_color": "DD2E44", 
        "profile_background_image_url": "http://pbs.twimg.com/profile_background_images/580868781628477441/kgwblI1m.jpg", 
        "profile_background_image_url_https": "https://pbs.twimg.com/profile_background_images/580868781628477441/kgwblI1m.jpg", 
        "profile_background_tile": true, 
        "profile_banner_url": "https://pbs.twimg.com/profile_banners/48599448/1428910030", 
        "profile_image_url": "http://pbs.twimg.com/profile_images/586977070888157184/TdSiGkzx_normal.jpg", 
        "profile_image_url_https": "https://pbs.twimg.com/profile_images/586977070888157184/TdSiGkzx_normal.jpg", 
        "profile_link_color": "DD2E44", 
        "profile_sidebar_border_color": "000000", 
        "profile_sidebar_fill_color": "161721", 
        "profile_text_color": "FFFFFF", 
        "profile_use_background_image": true, 
        "protected": false, 
        "screen_name": "barbls23", 
        "statuses_count": 59239, 
        "time_zone": "Eastern Time (US & Canada)", 
        "url": "http://t.co/eSqsUGB9Up", 
        "utc_offset": -14400, 
        "verified": false
    }
}